setup.py
quantgen/__init__.py
quantgen.egg-info/PKG-INFO
quantgen.egg-info/SOURCES.txt
quantgen.egg-info/dependency_links.txt
quantgen.egg-info/top_level.txt
quantgen/core/__init__.py
quantgen/core/chromosome.py
quantgen/core/diploidIndividual.py
quantgen/core/haplotype.py
quantgen/core/locus.py
quantgen/core/population.py
quantgen/sim/SLiM_reader.py
quantgen/sim/SLiM_writer.py
quantgen/sim/__init__.py
quantgen/test/__init__.py
quantgen/test/core/__init__.py
quantgen/test/core/chromosomeTest.py
quantgen/test/core/diploidIndividualTest.py
quantgen/test/core/haplotypeTest.py
quantgen/test/core/locusTest.py